CHANGES.txt
MANIFEST.in
README.rst
diary.rst
setup.py
isotoma/__init__.py
isotoma.plone.heroku.egg-info/PKG-INFO
isotoma.plone.heroku.egg-info/SOURCES.txt
isotoma.plone.heroku.egg-info/dependency_links.txt
isotoma.plone.heroku.egg-info/entry_points.txt
isotoma.plone.heroku.egg-info/namespace_packages.txt
isotoma.plone.heroku.egg-info/not-zip-safe
isotoma.plone.heroku.egg-info/requires.txt
isotoma.plone.heroku.egg-info/top_level.txt
isotoma/plone/__init__.py
isotoma/plone/heroku/__init__.py
isotoma/plone/heroku/instance.py
isotoma/plone/heroku/migrate.py
isotoma/plone/heroku/other.py
isotoma/plone/heroku/runner.py