Metadata-Version: 1.0
Name: isotoma.plone.heroku
Version: 0.0.0
Summary: Tooling for running Plone on heroku in a virtualenv
Home-page: UNKNOWN
Author: John Carr
Author-email: john.carr@isotoma.com
License: Apache Software License
Keywords: zope plone virtualenv foreman
Platform: UNKNOWN
Classifier: Intended Audience :: System Administrators
Classifier: Operating System :: POSIX
Classifier: License :: OSI Approved :: Apache Software License
